{
  "apiVersion": "v1",
  "kind": "Template",
  "labels": {},
  "metadata": {
    "annotations": {
      "description": "Minimalistic Apache Camel based Twitter photo streaming application",
      "iconClass": "icon-java"
    },
    "labels": {},
    "name": "camelympics"
  },
  "parameters": [
    {
      "name": "CONSUMER_KEY",
      "required": true,
      "description": "Twitter Consumer Key (API Key)"
    },
    {
      "name": "CONSUMER_SECRET",
      "required": true,
      "description": "Twitter Consumer Secret (API Secret)"
    },
    {
      "name": "ACCESS_TOKEN",
      "required": true,
      "description": "Twitter Access Token"
    },
    {
      "name": "ACCESS_TOKEN_SECRET",
      "required": true,
      "description": "Twitter Access Token Secret"
    },
    {
      "name": "SEARCH_TERM",
      "required": true,
      "description": "Twitter Search Term",
      "value": "sport"
    }
  ],
  "objects": [
    {
      "apiVersion": "v1",
      "kind": "Service",
      "metadata": {
        "annotations": {
          "prometheus.io/port": "9779",
          "prometheus.io/scrape": "true"
        },
        "labels": {
          "container": "java",
          "component": "${APP_NAME}",
          "provider": "s2i",
          "project": "${APP_NAME}",
          "version": "${APP_VERSION}",
          "group": "camelympics"
        },
        "name": "${SERVICE_NAME}"
      },
      "spec": {
        "clusterIP": "None",
        "deprecatedPublicIPs": [],
        "ports": [
          {
            "port": 1
          }
        ],
        "selector": {
          "container": "java",
          "project": "${APP_NAME}",
          "component": "${APP_NAME}",
          "provider": "s2i",
          "group": "camelympics"
        }
      }
    },
    {
      "kind": "ImageStream",
      "apiVersion": "v1",
      "metadata": {
        "name": "${APP_NAME}",
        "creationTimestamp": null,
        "labels": {
          "component": "${APP_NAME}",
          "container": "java",
          "group": "camelympics",
          "project": "${APP_NAME}",
          "provider": "s2i",
          "version": "${APP_VERSION}"
        }
      },
      "spec": {},
      "status": {
        "dockerImageRepository": ""
      }
    },
    {
      "kind": "BuildConfig",
      "apiVersion": "v1",
      "metadata": {
        "name": "${APP_NAME}",
        "creationTimestamp": null,
        "labels": {
          "component": "${APP_NAME}",
          "container": "java",
          "group": "camelympics",
          "project": "${APP_NAME}",
          "provider": "s2i",
          "version": "${APP_VERSION}"
        }
      },
      "spec": {
        "triggers": [
          {
            "type": "GitHub",
            "github": {
              "secret": "${BUILD_SECRET}"
            }
          },
          {
            "type": "Generic",
            "generic": {
              "secret": "${BUILD_SECRET}"
            }
          },
          {
            "type": "ConfigChange"
          },
          {
            "type": "ImageChange",
            "imageChange": {}
          }
        ],
        "source": {
          "type": "Git",
          "git": {
            "uri": "${GIT_REPO}",
            "ref": "${GIT_REF}"
          }
        },
        "strategy": {
          "type": "Source",
          "sourceStrategy": {
            "from": {
              "kind": "ImageStreamTag",
              "namespace": "${IMAGE_STREAM_NAMESPACE}",
              "name": "fis-java-openshift:${BUILDER_VERSION}"
            },
            "forcePull": true,
            "env": [
              {
                "name": "BUILD_LOGLEVEL",
                "value": "5"
              },
              {
                "name": "ARTIFACT_DIR",
                "value": "${ARTIFACT_DIR}"
              },
              {
                "name": "MAVEN_ARGS",
                "value": "${MAVEN_ARGS}"
              },
              {
                "name": "MAVEN_ARGS_APPEND",
                "value": "${MAVEN_ARGS_APPEND}"
              }
            ]
          }
        },
        "output": {
          "to": {
            "kind": "ImageStreamTag",
            "name": "${APP_NAME}:latest"
          }
        },
        "resources": {}
      },
      "status": {
        "lastVersion": 0
      }
    },
    {
      "kind": "DeploymentConfig",
      "apiVersion": "v1",
      "metadata": {
        "name": "${APP_NAME}",
        "creationTimestamp": null,
        "labels": {
          "component": "${APP_NAME}",
          "container": "java",
          "group": "camelympics",
          "project": "${APP_NAME}",
          "provider": "s2i",
          "version": "${APP_VERSION}"
        }
      },
      "spec": {
        "strategy": {
          "resources": {}
        },
        "triggers": [
          {
            "type": "ConfigChange"
          },
          {
            "type": "ImageChange",
            "imageChangeParams": {
              "automatic": true,
              "containerNames": [
                "${APP_NAME}"
              ],
              "from": {
                "kind": "ImageStreamTag",
                "name": "${APP_NAME}:latest"
              }
            }
          }
        ],
        "replicas": 1,
        "selector": {
          "component": "${APP_NAME}",
          "container": "java",
          "deploymentconfig": "${APP_NAME}",
          "group": "camelympics",
          "project": "${APP_NAME}",
          "provider": "s2i",
          "version": "${APP_VERSION}"
        },
        "template": {
          "metadata": {
            "creationTimestamp": null,
            "labels": {
              "component": "${APP_NAME}",
              "container": "java",
              "deploymentconfig": "${APP_NAME}",
              "group": "camelympics",
              "project": "${APP_NAME}",
              "provider": "s2i",
              "version": "${APP_VERSION}"
            }
          },
          "spec": {
            "containers": [
              {
                "name": "${APP_NAME}",
                "image": "library/${APP_NAME}:latest",
                "readinessProbe": {
                  "exec": {
                    "command": [
                      "/bin/bash",
                      "-c",
                      "(curl -f 127.0.0.1:8778) >/dev/null 2>&1; test $? != 7"
                    ]
                  },
                  "initialDelaySeconds": 30,
                  "timeoutSeconds": 5
                },
                "ports": [
                  {
                    "containerPort": 8778,
                    "name": "jolokia",
                    "protocol": "TCP"
                  }
                ],
                "resources": {}
              }
            ]
          }
        }
      },
      "status": {}
    }
  ]
}
